{
  "metadata" : {
    "identifier" : "https://truyenvnmoi.com/danh-mon-chi-ai",
    "title" : "Danh Môn Chí Ái",
    "subtitle" : null,
    "author" : null,
    "narrator" : null,
    "language" : "vi",
    "description" : null,
    "publisher" : "N/A",
    "subject" : null,
    "modified" : null,
    "published" : "2023-04-29",
    "duration" : 0,
    "abridged" : false,
    "conformsTo" : "https://readium.org/webpub-manifest/profiles/divina",
    "numberOfPages" : 460,
    "readingProgression" : "ttb",
    "belongsTo" : null,
    "presentation" : {
      "fit" : "width",
      "overflow" : "scrolled",
      "continuous" : true
    },
    "@type" : null,
    "schema:license" : null
  },
  "links" : [ {
    "rel" : "self",
    "href" : "https://raw.githubusercontent.com/thuvienonline40/book_storage_collection/main/comic_manifest.json",
    "type" : "application/divina+json"
  } ],
  "readingOrder" : [ {
    "href" : "https://img.abctruyen.xyz/uploads/6132/chuong-185/0.jpg",
    "type" : "image/jpeg",
    "bitrate" : 0,
    "duration" : 0,
    "title" : null,
    "properties" : null
  }, {
    "href" : "https://img.abctruyen.xyz/uploads/6132/chuong-185/1.jpg",
    "type" : "image/jpeg",
    "bitrate" : 0,
    "duration" : 0,
    "title" : null,
    "properties" : null
  }, {
    "href" : "https://img.abctruyen.xyz/uploads/6132/chuong-185/2.jpg",
    "type" : "image/jpeg",
    "bitrate" : 0,
    "duration" : 0,
    "title" : null,
    "properties" : null
  }, {
    "href" : "https://img.abctruyen.xyz/uploads/6132/chuong-185/3.jpg",
    "type" : "image/jpeg",
    "bitrate" : 0,
    "duration" : 0,
    "title" : null,
    "properties" : null
  }, {
    "href" : "https://img.abctruyen.xyz/uploads/6132/chuong-185/4.jpg",
    "type" : "image/jpeg",
    "bitrate" : 0,
    "duration" : 0,
    "title" : null,
    "properties" : null
  }, {
    "href" : "https://img.abctruyen.xyz/uploads/6132/chuong-185/5.jpg",
    "type" : "image/jpeg",
    "bitrate" : 0,
    "duration" : 0,
    "title" : null,
    "properties" : null
  }, {
    "href" : "https://img.abctruyen.xyz/uploads/6132/chuong-185/6.jpg",
    "type" : "image/jpeg",
    "bitrate" : 0,
    "duration" : 0,
    "title" : null,
    "properties" : null
  }, {
    "href" : "https://img.abctruyen.xyz/uploads/6132/chuong-185/7.jpg",
    "type" : "image/jpeg",
    "bitrate" : 0,
    "duration" : 0,
    "title" : null,
    "properties" : null
  }, {
    "href" : "https://img.abctruyen.xyz/uploads/6132/chuong-185/8.jpg",
    "type" : "image/jpeg",
    "bitrate" : 0,
    "duration" : 0,
    "title" : null,
    "properties" : null
  }, {
    "href" : "https://img.abctruyen.xyz/uploads/6132/chuong-185/9.jpg",
    "type" : "image/jpeg",
    "bitrate" : 0,
    "duration" : 0,
    "title" : null,
    "properties" : null
  }, {
    "href" : "https://img.abctruyen.xyz/uploads/6132/chuong-185/10.jpg",
    "type" : "image/jpeg",
    "bitrate" : 0,
    "duration" : 0,
    "title" : null,
    "properties" : null
  }, {
    "href" : "https://img.abctruyen.xyz/uploads/6132/chuong-185/11.jpg",
    "type" : "image/jpeg",
    "bitrate" : 0,
    "duration" : 0,
    "title" : null,
    "properties" : null
  }, {
    "href" : "https://img.abctruyen.xyz/uploads/6132/chuong-185/12.jpg",
    "type" : "image/jpeg",
    "bitrate" : 0,
    "duration" : 0,
    "title" : null,
    "properties" : null
  }, {
    "href" : "https://img.abctruyen.xyz/uploads/6132/chuong-185/13.jpg",
    "type" : "image/jpeg",
    "bitrate" : 0,
    "duration" : 0,
    "title" : null,
    "properties" : null
  }, {
    "href" : "https://img.abctruyen.xyz/uploads/6132/chuong-185/14.jpg",
    "type" : "image/jpeg",
    "bitrate" : 0,
    "duration" : 0,
    "title" : null,
    "properties" : null
  }, {
    "href" : "https://img.abctruyen.xyz/uploads/6132/chuong-185/15.jpg",
    "type" : "image/jpeg",
    "bitrate" : 0,
    "duration" : 0,
    "title" : null,
    "properties" : null
  }, {
    "href" : "https://img.abctruyen.xyz/uploads/6132/chuong-185/16.jpg",
    "type" : "image/jpeg",
    "bitrate" : 0,
    "duration" : 0,
    "title" : null,
    "properties" : null
  }, {
    "href" : "https://img.abctruyen.xyz/uploads/6132/chuong-185/17.jpg",
    "type" : "image/jpeg",
    "bitrate" : 0,
    "duration" : 0,
    "title" : null,
    "properties" : null
  }, {
    "href" : "https://img.abctruyen.xyz/uploads/6132/chuong-185/18.jpg",
    "type" : "image/jpeg",
    "bitrate" : 0,
    "duration" : 0,
    "title" : null,
    "properties" : null
  }, {
    "href" : "https://img.abctruyen.xyz/uploads/6132/chuong-185/19.jpg",
    "type" : "image/jpeg",
    "bitrate" : 0,
    "duration" : 0,
    "title" : null,
    "properties" : null
  }, {
    "href" : "https://img.abctruyen.xyz/uploads/6132/chuong-185/20.jpg",
    "type" : "image/jpeg",
    "bitrate" : 0,
    "duration" : 0,
    "title" : null,
    "properties" : null
  }, {
    "href" : "https://img.abctruyen.xyz/uploads/6132/chuong-185/21.jpg",
    "type" : "image/jpeg",
    "bitrate" : 0,
    "duration" : 0,
    "title" : null,
    "properties" : null
  }, {
    "href" : "https://img.abctruyen.xyz/uploads/6132/chuong-185/22.jpg",
    "type" : "image/jpeg",
    "bitrate" : 0,
    "duration" : 0,
    "title" : null,
    "properties" : null
  }, {
    "href" : "https://img.abctruyen.xyz/uploads/6132/chuong-185/23.jpg",
    "type" : "image/jpeg",
    "bitrate" : 0,
    "duration" : 0,
    "title" : null,
    "properties" : null
  }, {
    "href" : "https://img.abctruyen.xyz/uploads/6132/chuong-185/24.jpg",
    "type" : "image/jpeg",
    "bitrate" : 0,
    "duration" : 0,
    "title" : null,
    "properties" : null
  }, {
    "href" : "https://img.abctruyen.xyz/uploads/6132/chuong-185/25.jpg",
    "type" : "image/jpeg",
    "bitrate" : 0,
    "duration" : 0,
    "title" : null,
    "properties" : null
  }, {
    "href" : "https://img.abctruyen.xyz/uploads/6132/chuong-185/26.jpg",
    "type" : "image/jpeg",
    "bitrate" : 0,
    "duration" : 0,
    "title" : null,
    "properties" : null
  }, {
    "href" : "https://img.abctruyen.xyz/uploads/6132/chuong-185/27.jpg",
    "type" : "image/jpeg",
    "bitrate" : 0,
    "duration" : 0,
    "title" : null,
    "properties" : null
  }, {
    "href" : "https://img.abctruyen.xyz/uploads/6132/chuong-185/28.jpg",
    "type" : "image/jpeg",
    "bitrate" : 0,
    "duration" : 0,
    "title" : null,
    "properties" : null
  }, {
    "href" : "https://img.abctruyen.xyz/uploads/6132/chuong-185/29.jpg",
    "type" : "image/jpeg",
    "bitrate" : 0,
    "duration" : 0,
    "title" : null,
    "properties" : null
  }, {
    "href" : "https://img.abctruyen.xyz/uploads/6132/chuong-185/30.jpg",
    "type" : "image/jpeg",
    "bitrate" : 0,
    "duration" : 0,
    "title" : null,
    "properties" : null
  }, {
    "href" : "https://img.abctruyen.xyz/uploads/6132/chuong-185/31.jpg",
    "type" : "image/jpeg",
    "bitrate" : 0,
    "duration" : 0,
    "title" : null,
    "properties" : null
  }, {
    "href" : "https://img.abctruyen.xyz/uploads/6132/chuong-185/32.jpg",
    "type" : "image/jpeg",
    "bitrate" : 0,
    "duration" : 0,
    "title" : null,
    "properties" : null
  }, {
    "href" : "https://img.abctruyen.xyz/uploads/6132/chuong-185/33.jpg",
    "type" : "image/jpeg",
    "bitrate" : 0,
    "duration" : 0,
    "title" : null,
    "properties" : null
  }, {
    "href" : "https://img.abctruyen.xyz/uploads/6132/chuong-185/34.jpg",
    "type" : "image/jpeg",
    "bitrate" : 0,
    "duration" : 0,
    "title" : null,
    "properties" : null
  }, {
    "href" : "https://img.abctruyen.xyz/uploads/6132/chuong-185/35.jpg",
    "type" : "image/jpeg",
    "bitrate" : 0,
    "duration" : 0,
    "title" : null,
    "properties" : null
  }, {
    "href" : "https://img.abctruyen.xyz/uploads/6132/chuong-185/36.jpg",
    "type" : "image/jpeg",
    "bitrate" : 0,
    "duration" : 0,
    "title" : null,
    "properties" : null
  }, {
    "href" : "https://img.abctruyen.xyz/uploads/6132/chuong-185/37.jpg",
    "type" : "image/jpeg",
    "bitrate" : 0,
    "duration" : 0,
    "title" : null,
    "properties" : null
  }, {
    "href" : "https://img.abctruyen.xyz/uploads/6132/chuong-185/38.jpg",
    "type" : "image/jpeg",
    "bitrate" : 0,
    "duration" : 0,
    "title" : null,
    "properties" : null
  }, {
    "href" : "https://img.abctruyen.xyz/uploads/6132/chuong-185/39.jpg",
    "type" : "image/jpeg",
    "bitrate" : 0,
    "duration" : 0,
    "title" : null,
    "properties" : null
  }, {
    "href" : "https://img.abctruyen.xyz/uploads/6132/chuong-185/40.jpg",
    "type" : "image/jpeg",
    "bitrate" : 0,
    "duration" : 0,
    "title" : null,
    "properties" : null
  }, {
    "href" : "https://img.abctruyen.xyz/uploads/6132/chuong-185/41.jpg",
    "type" : "image/jpeg",
    "bitrate" : 0,
    "duration" : 0,
    "title" : null,
    "properties" : null
  }, {
    "href" : "https://img.abctruyen.xyz/uploads/6132/chuong-185/42.jpg",
    "type" : "image/jpeg",
    "bitrate" : 0,
    "duration" : 0,
    "title" : null,
    "properties" : null
  }, {
    "href" : "https://img.abctruyen.xyz/uploads/6132/chuong-185/43.jpg",
    "type" : "image/jpeg",
    "bitrate" : 0,
    "duration" : 0,
    "title" : null,
    "properties" : null
  }, {
    "href" : "https://img.abctruyen.xyz/uploads/6132/chuong-185/44.jpg",
    "type" : "image/jpeg",
    "bitrate" : 0,
    "duration" : 0,
    "title" : null,
    "properties" : null
  }, {
    "href" : "https://img.abctruyen.xyz/uploads/6132/chuong-185/45.jpg",
    "type" : "image/jpeg",
    "bitrate" : 0,
    "duration" : 0,
    "title" : null,
    "properties" : null
  }, {
    "href" : "https://img.abctruyen.xyz/uploads/6132/chuong-185/46.jpg",
    "type" : "image/jpeg",
    "bitrate" : 0,
    "duration" : 0,
    "title" : null,
    "properties" : null
  }, {
    "href" : "https://img.abctruyen.xyz/uploads/6132/chuong-185/47.jpg",
    "type" : "image/jpeg",
    "bitrate" : 0,
    "duration" : 0,
    "title" : null,
    "properties" : null
  }, {
    "href" : "https://i2.wp.com/truyenvnhot.net/wp-content/uploads/2022/12/truyenvn-gg-banner.jpg",
    "type" : "image/jpeg",
    "bitrate" : 0,
    "duration" : 0,
    "title" : null,
    "properties" : null
  } ],
  "toc" : null,
  "@context" : "https://readium.org/webpub-manifest/context.jsonld"
}