{
  "metadata" : {
    "identifier" : "https://nghetruyenma.net/hon-ai-tro-ve.html",
    "title" : "Hồn Ai Trở Về",
    "subtitle" : "N/A",
    "author" : {
      "name" : "Hoàng Kiên",
      "sortAs" : ""
    },
    "narrator" : "N/A",
    "language" : "vi",
    "description" : "N/A",
    "publisher" : "N/A",
    "subject" : null,
    "modified" : null,
    "published" : "2023-06-27",
    "duration" : 3856,
    "abridged" : false,
    "conformsTo" : null,
    "numberOfPages" : null,
    "readingProgression" : null,
    "belongsTo" : null,
    "presentation" : null,
    "@type" : "http://schema.org/Audiobook",
    "schema:license" : "https://creativecommons.org/publicdomain/zero/1.0/"
  },
  "links" : [ {
    "rel" : "self",
    "href" : "https://raw.githubusercontent.com/vietduyhuynh90s/book_storage_two6/main/EPUB/EPUB_41272caaab48d250becb38e774064ec2.json",
    "type" : "application/audiobook+json"
  }, {
    "rel" : "cover",
    "href" : "https://raw.githubusercontent.com/vietduyhuynh90s/book_storage_two6/main/IMAGE/IMAGE_41272caaab48d250becb38e774064ec2.webp",
    "type" : "image/jpeg",
    "height" : 300,
    "width" : 300
  } ],
  "readingOrder" : [ {
    "href" : "https://archive.org/download/honaitrove/honaitrove.mp3",
    "type" : "audio/mpeg",
    "bitrate" : 128,
    "duration" : 3856,
    "title" : "honaitrove",
    "properties" : null,
    "alternate" : null
  } ],
  "toc" : [ {
    "href" : "https://archive.org/download/honaitrove/honaitrove.mp3",
    "title" : "honaitrove",
    "children" : [ ]
  } ],
  "@context" : "https://readium.org/webpub-manifest/context.jsonld"
}