{
  "metadata" : {
    "identifier" : "https://www.dtv-ebook.com/thang-khung-james-hadley-chase_10151.html",
    "title" : "Thằng Khùng - James Hadley Chase.",
    "subtitle" : "N/A",
    "author" : {
      "name" : "James H. Chase",
      "sortAs" : ""
    },
    "narrator" : "N/A",
    "language" : "vi",
    "description" : "<p>N/A</p>",
    "publisher" : "N/A",
    "subject" : null,
    "modified" : null,
    "published" : "2023-05-09",
    "duration" : 23482,
    "abridged" : false,
    "conformsTo" : null,
    "numberOfPages" : null,
    "readingProgression" : null,
    "belongsTo" : null,
    "presentation" : null,
    "@type" : "http://schema.org/Audiobook",
    "schema:license" : "https://creativecommons.org/publicdomain/zero/1.0/"
  },
  "links" : [ {
    "rel" : "self",
    "href" : "https://raw.githubusercontent.com/vietduyhuynh90s/book_storage_two6/main/EPUB/EPUB_72ed87cddd74fe6f27acb14f4328a5b2.json",
    "type" : "application/audiobook+json"
  }, {
    "rel" : "cover",
    "href" : "https://raw.githubusercontent.com/vietduyhuynh90s/book_storage_two6/main/IMAGE/IMAGE_72ed87cddd74fe6f27acb14f4328a5b2.jpg",
    "type" : "image/jpeg",
    "height" : 300,
    "width" : 300
  } ],
  "readingOrder" : [ {
    "href" : "https://archive.org/download/thangkhung/1.mp3",
    "type" : "audio/mpeg",
    "bitrate" : 128,
    "duration" : 3437,
    "title" : "1",
    "properties" : null,
    "alternate" : null
  }, {
    "href" : "https://archive.org/download/thangkhung/2.mp3",
    "type" : "audio/mpeg",
    "bitrate" : 128,
    "duration" : 2661,
    "title" : "2",
    "properties" : null,
    "alternate" : null
  }, {
    "href" : "https://archive.org/download/thangkhung/3.mp3",
    "type" : "audio/mpeg",
    "bitrate" : 128,
    "duration" : 2572,
    "title" : "3",
    "properties" : null,
    "alternate" : null
  }, {
    "href" : "https://archive.org/download/thangkhung/4.mp3",
    "type" : "audio/mpeg",
    "bitrate" : 128,
    "duration" : 2365,
    "title" : "4",
    "properties" : null,
    "alternate" : null
  }, {
    "href" : "https://archive.org/download/thangkhung/5.mp3",
    "type" : "audio/mpeg",
    "bitrate" : 128,
    "duration" : 2923,
    "title" : "5",
    "properties" : null,
    "alternate" : null
  }, {
    "href" : "https://archive.org/download/thangkhung/6.mp3",
    "type" : "audio/mpeg",
    "bitrate" : 128,
    "duration" : 2800,
    "title" : "6",
    "properties" : null,
    "alternate" : null
  }, {
    "href" : "https://archive.org/download/thangkhung/7.mp3",
    "type" : "audio/mpeg",
    "bitrate" : 128,
    "duration" : 3213,
    "title" : "7",
    "properties" : null,
    "alternate" : null
  }, {
    "href" : "https://archive.org/download/thangkhung/8.mp3",
    "type" : "audio/mpeg",
    "bitrate" : 128,
    "duration" : 2461,
    "title" : "8",
    "properties" : null,
    "alternate" : null
  }, {
    "href" : "https://archive.org/download/thangkhung/9.mp3",
    "type" : "audio/mpeg",
    "bitrate" : 128,
    "duration" : 1050,
    "title" : "9",
    "properties" : null,
    "alternate" : null
  } ],
  "toc" : [ {
    "href" : "https://archive.org/download/thangkhung/1.mp3",
    "title" : "1",
    "children" : [ ]
  }, {
    "href" : "https://archive.org/download/thangkhung/2.mp3",
    "title" : "2",
    "children" : [ ]
  }, {
    "href" : "https://archive.org/download/thangkhung/3.mp3",
    "title" : "3",
    "children" : [ ]
  }, {
    "href" : "https://archive.org/download/thangkhung/4.mp3",
    "title" : "4",
    "children" : [ ]
  }, {
    "href" : "https://archive.org/download/thangkhung/5.mp3",
    "title" : "5",
    "children" : [ ]
  }, {
    "href" : "https://archive.org/download/thangkhung/6.mp3",
    "title" : "6",
    "children" : [ ]
  }, {
    "href" : "https://archive.org/download/thangkhung/7.mp3",
    "title" : "7",
    "children" : [ ]
  }, {
    "href" : "https://archive.org/download/thangkhung/8.mp3",
    "title" : "8",
    "children" : [ ]
  }, {
    "href" : "https://archive.org/download/thangkhung/9.mp3",
    "title" : "9",
    "children" : [ ]
  } ],
  "@context" : "https://readium.org/webpub-manifest/context.jsonld"
}